_cfsa.pypy311-pp73-darwin.so
convolutionalfixedsum/itp.py
convolutionalfixedsum/cfsvr.py
convolutionalfixedsum/dcfs.py
convolutionalfixedsum/__init__.py
convolutionalfixedsum/cfsa.py
convolutionalfixedsum/build_cfsa.py
convolutionalfixedsum/analytical/itp.c
convolutionalfixedsum/analytical/pluggable_rand.c
convolutionalfixedsum/analytical/ivorfixedsum.c
convolutionalfixedsum/analytical/fsum.c
convolutionalfixedsum/analytical/xoroshiro256sp.c
convolutionalfixedsum/analytical/ivrfs_vc.c
convolutionalfixedsum-2.0.dist-info/RECORD
convolutionalfixedsum-2.0.dist-info/WHEEL
convolutionalfixedsum-2.0.dist-info/top_level.txt
convolutionalfixedsum-2.0.dist-info/METADATA
convolutionalfixedsum-2.0.dist-info/licenses/LICENSE
