Metadata-Version: 2.4
Name: convolutionalfixedsum
Version: 2.0
Summary: Algorithm to generate uniformly sampled random vectors which sum to a given value, with constraints on each variate
Author-email: David Griffin <dgdguk@gmail.com>
License-Expression: BSD-3-Clause
Project-URL: Homepage, https://github.com/dgdguk/convolutionalfixedsum
Project-URL: Issues, https://github.com/dgdguk/convolutionalfixedsum/issues
Classifier: Programming Language :: Python :: 3
Classifier: Operating System :: OS Independent
Requires-Python: >=3.10
License-File: LICENSE
Requires-Dist: numpy>=2.2.5
Requires-Dist: scipy>=1.15
Requires-Dist: cffi>=1.17
Dynamic: license-file
